webp/__init__.py
webp/_webp.pyd
webp/py.typed
webp-0.4.0.dist-info/LICENSE
webp-0.4.0.dist-info/METADATA
webp-0.4.0.dist-info/WHEEL
webp-0.4.0.dist-info/top_level.txt
webp-0.4.0.dist-info/RECORD
