Metadata-Version: 2.1
Name: webp
Version: 0.4.0
Summary: Python bindings for WebP
Author-email: Aiden Nibali <dismaldenizen@gmail.com>
License: MIT
Project-URL: Homepage, https://github.com/anibali/pywebp
Classifier: Programming Language :: Python :: 3 :: Only
Classifier: Topic :: Multimedia :: Graphics :: Graphics Conversion
Classifier: License :: OSI Approved :: MIT License
Requires-Python: >=3.8
License-File: LICENSE
Requires-Dist: Pillow >=4.0.0
Requires-Dist: cffi >=1.12
Requires-Dist: numpy >=1.0.0
Provides-Extra: dev
Requires-Dist: build >=1.0.0 ; extra == 'dev'
Requires-Dist: conan >=2.0 ; extra == 'dev'
Requires-Dist: conda-lock >=2.0.0 ; extra == 'dev'
Requires-Dist: twine ; extra == 'dev'
Provides-Extra: test
Requires-Dist: pytest ; extra == 'test'
